{
    "bitflyer": {
        "BTC": {
            "price": 713359,
            "lastTime": 1585326510,
            "open": 1017485,
            "high": 1019418,
            "low": 1017436,
            "close": 1018792,
            "qty": 73.64142933
        }
    },
    "bitmex": {
        "BTC": {
            "price": 8748,
            "lastTime": 1579109940,
            "open": 8746.5,
            "high": 8748,
            "low": 8746.5,
            "close": 8748,
            "qty": 304709
        }
    }
}